<?xml version="1.0" encoding="UTF-8"?>
<plate>
   <head>
<doctype>html5</doctype>
      <meta http-equiv="Content-Type" content="text/html;charset=utf-8" />
      <meta http-equiv="X-UA-Compatible" content="IE=edge" />
      <meta name="viewport" content="width=device-width, initial-scale=1" />
      <script src="//cdn.muicss.com/mui-0.2.3/js/mui.min.js" />
      <script src="//cdn.muicss.com/mui-0.2.3/webcomponents/mui-webcomponents.js" />
      <script src="https://use.fontawesome.com/9005b8ab53.js" />
      <script src="https://maps.googleapis.com/maps/api/js?key=AIzaSyDdpVzvchiUZno_vZsAtM5JwQWNGhMCNgA" />
   </head>
   <clippings />
   <ingredients>
      <dataset name="clippings" name_friendly="Clippings">
         <fields>
            <text name="site_name" name_friendly="Site Name" required="1" />
            <images name="logo" name_friendly="Site Logo" limit="1" />
            <text name="footer_text" name_friendly="Footer Text" />
         </fields>
         <items>
            <item>
               <text name="site_name" name_friendly="Site Name" required="1"><![CDATA[ZestyBurger]]></text>
               <images name="logo" name_friendly="Site Logo" limit="1" />
               <text name="footer_text" name_friendly="Footer Text"><![CDATA[Burger by Zesty]]></text>
            </item>
         </items>
      </dataset>
      <templateset name="homepage" name_friendly="Homepage" view="homepage">
         <fields>
            <text name="splash_title" name_friendly="Splash Title" required="1" />
            <text name="splash_description" name_friendly="Splash Description" required="1" />
            <text name="splash_link" name_friendly="Splash Link" required="1" />
            <text name="splash_link_text" name_friendly="Splash Link Text" required="1" />
            <images name="splash_background" name_friendly="Splash Background" required="1" />
         </fields>
         <items>
            <splash_title><![CDATA[Eat Zesty]]></splash_title>
            <splash_description><![CDATA[Come and taste the burger revolution at any of our award winning restaurants worldwide.]]></splash_description>
            <splash_link><![CDATA[http://burger.zesty.site/locations/]]></splash_link>
            <splash_link_text><![CDATA[Find a Location Near You]]></splash_link_text>
            <splash_background><![CDATA[https://6c706l48.media.zestyio.com/bg_3.f1cb27a519bdb5b6ed34049a5b86e317.jpg]]></splash_background>
         </items>
      </templateset>
   </ingredients>
</plate>